svenson/__init__.py
svenson/common.py
svenson/svenson.py
svenson-0.0.1.dist-info/LICENSE
svenson-0.0.1.dist-info/METADATA
svenson-0.0.1.dist-info/WHEEL
svenson-0.0.1.dist-info/entry_points.txt
svenson-0.0.1.dist-info/top_level.txt
svenson-0.0.1.dist-info/RECORD
