Metadata-Version: 2.2
Name: svenson
Version: 0.0.1
Summary: svenson is a test project for trainning purpose
Author-email: kunmi Adebanjo <kunmi.i.a@outlook.com>
License: MIT License
Project-URL: Homepage, https://github.com/khunmi/svenson
Keywords: svenson
Classifier: Intended Audience :: Developers
Classifier: License :: OSI Approved :: MIT License
Classifier: Natural Language :: English
Classifier: Programming Language :: Python :: 3.8
Classifier: Programming Language :: Python :: 3.9
Classifier: Programming Language :: Python :: 3.10
Classifier: Programming Language :: Python :: 3.11
Classifier: Programming Language :: Python :: 3.12
Requires-Python: >=3.8
License-File: LICENSE
Requires-Dist: numpy
Provides-Extra: all
Requires-Dist: svenson[extra]; extra == "all"
Provides-Extra: extra
Requires-Dist: pandas; extra == "extra"
